MANIFEST.in
README.md
setup.cfg
setup.py
pymgit/__init__.py
pymgit/cli.py