Metadata-Version: 1.1
Name: pymgit
Version: 0.1.0
Summary: A command-line tool to clone multiple Git repositories and checkout specific branches/tags
Home-page: https://github.com/watsonb/pymgit
Author: Ben Watson
Author-email: bwatson1979@gmail.com
License: MIT
Keywords: cli
Platform: UNKNOWN
Classifier: Intended Audience :: Developers
Classifier: Topic :: Utilities
Classifier: License :: Public Domain
Classifier: Natural Language :: English
Classifier: Operating System :: OS Independent
Classifier: Programming Language :: Python :: 2
Classifier: Programming Language :: Python :: 2.6
Classifier: Programming Language :: Python :: 2.7
Classifier: Programming Language :: Python :: 3
Classifier: Programming Language :: Python :: 3.2
Classifier: Programming Language :: Python :: 3.3
Classifier: Programming Language :: Python :: 3.4
